AUTHORS.rst
CHANGELOG.rst
LICENSE
MANIFEST.in
README.rst
setup.py
django_section.egg-info/PKG-INFO
django_section.egg-info/SOURCES.txt
django_section.egg-info/dependency_links.txt
django_section.egg-info/not-zip-safe
django_section.egg-info/requires.txt
django_section.egg-info/top_level.txt
section/__init__.py
section/context_processors.py
section/models.py
section/tests/__init__.py
section/tests/urls.py
section/tests/views.py